ga4gh/va_spec/__init__.py
ga4gh/va_spec/aac_2017/__init__.py
ga4gh/va_spec/aac_2017/models.py
ga4gh/va_spec/acmg_2015/__init__.py
ga4gh/va_spec/acmg_2015/models.py
ga4gh/va_spec/base/__init__.py
ga4gh/va_spec/base/core.py
ga4gh/va_spec/base/domain_entities.py
ga4gh/va_spec/base/enums.py
ga4gh/va_spec/base/validators.py
ga4gh/va_spec/ccv_2022/__init__.py
ga4gh/va_spec/ccv_2022/models.py
ga4gh_va_spec-0.4.2.dist-info/licenses/LICENSE
ga4gh_va_spec-0.4.2.dist-info/METADATA
ga4gh_va_spec-0.4.2.dist-info/WHEEL
ga4gh_va_spec-0.4.2.dist-info/top_level.txt
ga4gh_va_spec-0.4.2.dist-info/RECORD
