Metadata-Version: 2.4
Name: ga4gh.va_spec
Version: 0.4.2
Summary: GA4GH Variant Annotation (VA) reference implementation
Author: Matt Brush, Javier Lopez
License:                                  Apache License
Project-URL: Homepage, https://github.com/ga4gh/va-spec-python
Project-URL: Documentation, https://github.com/ga4gh/va-spec-python
Project-URL: Changelog, https://github.com/ga4gh/va-spec-python/releases
Project-URL: Source, https://github.com/ga4gh/va-spec-python
Project-URL: Bug Tracker, https://github.com/ga4gh/va-spec-python/issues
Keywords: bioinformatics,ga4gh,genomics,variation
Classifier: Development Status :: 3 - Alpha
Classifier: Intended Audience :: Developers
Classifier: Intended Audience :: Healthcare Industry
Classifier: Intended Audience :: Science/Research
Classifier: License :: OSI Approved :: Apache Software License
Classifier: Operating System :: OS Independent
Classifier: Programming Language :: Python
Classifier: Programming Language :: Python :: 3
Classifier: Programming Language :: Python :: 3.10
Classifier: Programming Language :: Python :: 3.11
Classifier: Programming Language :: Python :: 3.12
Classifier: Topic :: Scientific/Engineering :: Bio-Informatics
Classifier: Topic :: Scientific/Engineering :: Medical Science Apps.
Requires-Python: >=3.10
License-File: LICENSE
Requires-Dist: ga4gh.vrs<3.0,>=2.1.3
Requires-Dist: ga4gh.cat_vrs~=0.7.1
Requires-Dist: pydantic<3.0,>=2.0
Provides-Extra: dev
Requires-Dist: pre-commit; extra == "dev"
Requires-Dist: ruff==0.4.9; extra == "dev"
Provides-Extra: tests
Requires-Dist: pytest; extra == "tests"
Requires-Dist: pytest-cov; extra == "tests"
Requires-Dist: pyyaml; extra == "tests"
Provides-Extra: notebooks
Requires-Dist: jupyter; extra == "notebooks"
Dynamic: license-file
